Workbook

Sheet ICT Projects - Consolidated
A1: Region | B1: Project ID | C1: Project / Scheme Name | D1: Sector / Division | E1: Sub-Sector | F1: Ministry / Department / Authority | G1: Location | H1: Status | I1: Total Project Cost (M PKR) | J1: FY2026-27 Allocation (M PKR) | K1: ICT Involvement % | L1: ICT Level / Category | M1: ICT TAM on Allocation (M PKR) | N1: ICT TAM on Total Cost (M PKR) | O1: ICT Reasoning | P1: Fixed Connectivity | Q1: GSM / Devices | R1: Cloud | S1: Cyber Security | T1: Servers / Internet | U1: Fiber / Broadband | V1: CCTV Camera | W1: IoT | X1: SIMs (GSM/CMT) | Y1: SMS / Messaging | Z1: Source File | AA1: Source Sheet
A2: KPK (Provincial ADP) | B2: 190219 | C2: Khyber Pakhtunkhwa Cities Improvement Project (ADB Assisted) | D2: Urban Development | E2: Urban Development | H2: Ongoing | I2: 105196.58 | J2: 18117.5 | K2: 0.05 | L2: Low | M2: 25 | N2: 5259.829 | O2: Institutional/reform programme - realistic minor MIS/digital & connectivity component | P2: Yes | Q2: Yes | Z2: KPK_ADP_2026-27_ICT_Opportunity.xlsx | AA2: ICT Projects
A3: KPK (Provincial ADP) | B3: 261278 | C3: Strengthening of Police, CTD , District Administration and Judiciary in Security Challenged Districts | D3: Home | E3: HTAs | H3: New | I3: 20000 | J3: 12000 | K3: 0.05 | L3: Low | M3: 600 | N3: 1000 | O3: Institutional/reform programme - realistic minor MIS/digital & connectivity component | P3: Yes | Q3: Yes | V3: Yes | X3: Yes | Z3: KPK_ADP_2026-27_ICT_Opportunity.xlsx | AA3: ICT Projects
A4: KPK (Provincial ADP) | B4: 220569 | C4: Khyber Pakhtunkhwa Health Strengthening Programme (SBS) for Revamping of Non-Teaching DHQ Hospital | D4: Health | E4: General Hospitals | H4: New | I4: 28000.003 | J4: 8700.001 | K4: 0.3 | L4: Medium | M4: 0.0003 | N4: 8400.0009 | O4: ICT-enabled: strengtheninghospitalhealth facilithealth informationsurveillance; Facility: bhospitalsb, bthqbbdhqbbrhcbbbhubbmchbcivil hospitals | P4: Yes | Q4: Yes | T4: Yes | V4: Yes | Z4: KPK_ADP_2026-27_ICT_Opportunity.xlsx | AA4: ICT Projects
A5: KPK (Provincial ADP) | B5: 200166 | C5: Refugees & Host Communities under IDA-18-Regional Sub Window SH: Khyber Pakhtunkhwa Human Capital Investment Project (KPHCIP) Education Component | D5: Elementary & Secondary Education | E5: E&SE Department | H5: Ongoing | I5: 32834.003 | J5: 8700.001 | K5: 0.05 | L5: Low | M5: 5e-05 | N5: 1641.7001 | O5: Institutional/reform programme - realistic minor MIS/digital & connectivity component | P5: Yes | Q5: Yes | Z5: KPK_ADP_2026-27_ICT_Opportunity.xlsx | AA5: ICT Projects
A6: KPK (Provincial ADP) | B6: 261146 | C6: Khyber Pakhtunkhwa Public Resource for Inclusive Development Multiphase programmatic Approach (KP-PRID-MPA) | D6: Finance | E6: Finance | H6: New | I6: 58000.003 | J6: 5800.001 | K6: 0.05 | L6: Low | M6: 5e-05 | N6: 2900.0001 | O6: Institutional/reform programme - realistic minor MIS/digital & connectivity component | P6: Yes | Q6: Yes | Z6: KPK_ADP_2026-27_ICT_Opportunity.xlsx | AA6: ICT Projects
A7: KPK (Provincial ADP) | B7: 210631 | C7: Khyber Pakhtunkhwa Rural Investment & Institutional Support Project (RIISP)(World Bank Assisted) | D7: Multi Sectoral Development | E7: MSD | H7: Ongoing | I7: 139698 | J7: 4467.7 | K7: 0.05 | L7: Low | M7: 5.885 | N7: 6984.9 | O7: Institutional/reform programme - realistic minor MIS/digital & connectivity component | P7: Yes | Q7: Yes | Z7: KPK_ADP_2026-27_ICT_Opportunity.xlsx | AA7: ICT Projects
A8: KPK (Provincial ADP) | B8: 170539 | C8: Khyber Pakhtunkhwa Integrated Tourism Development Project (KITE) (IDA Assisted) | D8: Tourism | E8: Tourism | H8: Ongoing | I8: 27303.804 | J8: 3000 | K8: 0.05 | L8: Low | M8: 5 | N8: 1365.1902 | O8: Institutional/reform programme - realistic minor MIS/digital & connectivity component | P8: Yes | Q8: Yes | Z8: KPK_ADP_2026-27_ICT_Opportunity.xlsx | AA8: ICT Projects
A9: KPK (Provincial ADP) | B9: 250870 | C9: Capacity Building and Development of Police and CTD Infrastructure in Merged Districts Phase-I | D9: Home | E9: Police | H9: Ongoing | I9: 8864.23 | J9: 2000 | K9: 0.05 | L9: Low | M9: 100 | N9: 443.2115 | O9: Institutional/reform programme - realistic minor MIS/digital & connectivity component | P9: Yes | Q9: Yes | V9: Yes | X9: Yes | Z9: KPK_ADP_2026-27_ICT_Opportunity.xlsx | AA9: ICT Projects
A10: KPK (Provincial ADP) | B10: 251564 | C10: Capacity Building and Development of Police and CTD Infrastructure in Merged Districts Phase-II | D10: Home | E10: Police | H10: Ongoing | I10: 7475.328 | J10: 2000 | K10: 0.05 | L10: Low | M10: 100 | N10: 373.7664 | O10: Institutional/reform programme - realistic minor MIS/digital & connectivity component | P10: Yes | Q10: Yes | V10: Yes | X10: Yes | Z10: KPK_ADP_2026-27_ICT_Opportunity.xlsx | AA10: ICT Projects
A11: KPK (Provincial ADP) | B11: 210287 | C11: Revamping of Secondary Health Facilities including Improvement of Accident and Emergency Units in Newly Merged Districts (AIP) | D11: Health | E11: General Hospitals | H11: Ongoing | I11: 7432.934 | J11: 1800 | K11: 0.05 | L11: Low | M11: 90 | N11: 371.6467 | O11: Facility: bhospitalsb, health facilityfacilitiescentrecenterunitcomplexcare | P11: Yes | Q11: Yes | V11: Yes | Z11: KPK_ADP_2026-27_ICT_Opportunity.xlsx | AA11: ICT Projects
A12: KPK (Provincial ADP) | B12: 210415 | C12: Khyber Pakhtunkhwa Spending Efficiently for Enhanced Development (SPEED) (IDA Assisted) | D12: Finance | E12: Finance | H12: Ongoing | I12: 112000 | J12: 1189.001 | K12: 0.05 | L12: Low | M12: 5e-05 | N12: 5600.0001 | O12: Institutional/reform programme - realistic minor MIS/digital & connectivity component | P12: Yes | Q12: Yes | Z12: KPK_ADP_2026-27_ICT_Opportunity.xlsx | AA12: ICT Projects
A13: KPK (Provincial ADP) | B13: 251629 | C13: Establishment of District Setup of Counter Terrorism Department at Khyber Pakhtunkhwa including construction of Peshawar Regional CTD Headquarters (Non-ADP) | D13: Home | E13: Police | H13: Ongoing | I13: 6441.34 | J13: 1008.14 | K13: 0.05 | L13: Low | M13: 50.407 | N13: 322.067 | O13: Facility: bofficesbbcomplexesbheadquartersecretariatdirectorate, establishment ofdepartmentauthoritycellunitwingofficedirectorateinstitute | P13: Yes | Q13: Yes | V13: Yes | X13: Yes | Z13: KPK_ADP_2026-27_ICT_Opportunity.xlsx | AA13: ICT Projects
A14: KPK (Provincial ADP) | B14: 210410 | C14: Institutional Development through innovative interventions | D14: Multi Sectoral Development | E14: Economic Infrastructural Development | H14: New | I14: 2000 | J14: 1000 | K14: 0.05 | L14: Low | M14: 50 | N14: 100 | O14: Institutional/reform programme - realistic minor MIS/digital & connectivity component | P14: Yes | Q14: Yes | Z14: KPK_ADP_2026-27_ICT_Opportunity.xlsx | AA14: ICT Projects
A15: KPK (Provincial ADP) | B15: 251628 | C15: Strengthening CTD's Mobility, Arms, Equipment and overall Modern Response Architecture (Non-ADP Approved) | D15: Home | E15: Police | H15: Ongoing | I15: 7770.34 | J15: 969.032 | K15: 0.05 | L15: Low | M15: 48.4516 | N15: 388.517 | O15: Institutional/reform programme - realistic minor MIS/digital & connectivity component | P15: Yes | Q15: Yes | V15: Yes | X15: Yes | Z15: KPK_ADP_2026-27_ICT_Opportunity.xlsx | AA15: ICT Projects
A16: KPK (Provincial ADP) | B16: 200197 | C16: Up-gradation of IRNUM PET-CT/Cyclotrom Project. | D16: Health | E16: General Hospitals | H16: Ongoing | I16: 2172.22 | J16: 900 | K16: 0.05 | L16: Low | M16: 45 | N16: 108.611 | O16: Facility: bhospitalsb | P16: Yes | Q16: Yes | V16: Yes | Z16: KPK_ADP_2026-27_ICT_Opportunity.xlsx | AA16: ICT Projects
A17: KPK (Provincial ADP) | B17: 210123 | C17: Strengthening of DHQ Hospitals (Building, Capacity to Respond Covid-19/any future Pandemic in Khyber Pakhtunkhwa (50% Provincial Share). | D17: Health | E17: General Hospitals | H17: Ongoing | I17: 8758.048 | J17: 890.667 | K17: 0.3 | L17: Medium | M17: 267.2001 | N17: 2627.4144 | O17: ICT-enabled: strengtheninghospitalhealth facilithealth informationsurveillance; Facility: bhospitalsb, bthqbbdhqbbrhcbbbhubbmchbcivil hospitals | P17: Yes | Q17: Yes | T17: Yes | V17: Yes | Z17: KPK_ADP_2026-27_ICT_Opportunity.xlsx | AA17: ICT Projects
A18: KPK (Provincial ADP) | B18: 240233 | C18: Establishment of Cath Labs at different hospitals of the Province on need basis | D18: Health | E18: General Hospitals | H18: Ongoing | I18: 1932.154 | J18: 800 | K18: 0.3 | L18: Medium | M18: 240 | N18: 579.6462 | O18: ICT-enabled: angiographycath labbmribbct scanb; Facility: bhospitalsb, establishmentuniversitycollegeschoolhospitalinstitutecenter | P18: Yes | Q18: Yes | T18: Yes | V18: Yes | Z18: KPK_ADP_2026-27_ICT_Opportunity.xlsx | AA18: ICT Projects
A19: KPK (Provincial ADP) | B19: 200049 | C19: Revamping of Non-Teaching DHQs across KP. | D19: Health | E19: General Hospitals | H19: Ongoing | I19: 7010.104 | J19: 799.999 | K19: 0.05 | L19: Low | M19: 39.99995 | N19: 350.5052 | O19: Facility: bhospitalsb | P19: Yes | Q19: Yes | V19: Yes | Z19: KPK_ADP_2026-27_ICT_Opportunity.xlsx | AA19: ICT Projects
A20: KPK (Provincial ADP) | B20: 210121 | C20: Strengthening of 12 DHQ Hospitals (Building Capacity to respond to Covid-19 / any future pandemic) in Khyber Pakhtunkhwa. (50% Provincial Share) | D20: Health | E20: General Hospitals | H20: Ongoing | I20: 9883.979 | J20: 780 | K20: 0.3 | L20: Medium | M20: 234 | N20: 2965.1937 | O20: ICT-enabled: strengtheninghospitalhealth facilithealth informationsurveillance; Facility: bhospitalsb, bthqbbdhqbbrhcbbbhubbmchbcivil hospitals | P20: Yes | Q20: Yes | T20: Yes | V20: Yes | Z20: KPK_ADP_2026-27_ICT_Opportunity.xlsx | AA20: ICT Projects
A21: KPK (Provincial ADP) | B21: 140150 | C21: Safe City Project Peshawar | D21: Home | E21: Police | H21: Ongoing | I21: 6974.79 | J21: 700 | K21: 0.7 | L21: High | M21: 490 | N21: 4882.353 | O21: Core-ICT: safe city | P21: Yes | Q21: Yes | R21: Yes | S21: Yes | T21: Yes | U21: Yes | V21: Yes | W21: Yes | X21: Yes | Z21: KPK_ADP_2026-27_ICT_Opportunity.xlsx | AA21: ICT Projects
A22: KPK (Provincial ADP) | B22: 260714 | C22: Establishment of Chief Minister Model Schools in Khyber Pakhtunkhwa (Phase-I) | D22: Elementary & Secondary Education | E22: E&SE Department | H22: New | I22: 6500 | J22: 700 | K22: 0.05 | L22: Low | M22: 35 | N22: 325 | O22: Facility: bschoolsb, establishment ofdepartmentauthoritycellunitwingofficedirectorateinstitute, establishmentuniversitycollegeschoolhospitalinstitutecenter | P22: Yes | Q22: Yes | V22: Yes | Z22: KPK_ADP_2026-27_ICT_Opportunity.xlsx | AA22: ICT Projects
A23: KPK (Provincial ADP) | B23: 251638 | C23: Establishment of Nursing College in the existing building of Regional Professional Development Centre (Female) at Jamrud Khyber | D23: Health | E23: Medical Education & Trg. | H23: Ongoing | I23: 635.487 | J23: 635.487 | K23: 0.05 | L23: Low | M23: 31.77435 | N23: 31.77435 | O23: Facility: bcollegesb, establishmentuniversitycollegeschoolhospitalinstitutecenter | P23: Yes | Q23: Yes | V23: Yes | Z23: KPK_ADP_2026-27_ICT_Opportunity.xlsx | AA23: ICT Projects
A24: KPK (Provincial ADP) | B24: 170331 | C24: Establishment of Forensic Science Laboratory (FSL) at Peshawar | D24: Home | E24: HTAs | H24: Ongoing | I24: 6887.64 | J24: 600 | K24: 0.05 | L24: Low | M24: 30 | N24: 344.382 | O24: Facility: bassemblybparliamentresearch stationinstitutecentercentreblaborator | P24: Yes | Q24: Yes | Z24: KPK_ADP_2026-27_ICT_Opportunity.xlsx | AA24: ICT Projects
A25: KPK (Provincial ADP) | B25: 150659 | C25: Institutional Support to P&D Department | D25: Multi Sectoral Development | E25: Research & Development | H25: Ongoing | I25: 2228 | J25: 591 | K25: 0.05 | L25: Low | M25: 29.55 | N25: 111.4 | O25: Institutional/reform programme - realistic minor MIS/digital & connectivity component | P25: Yes | Q25: Yes | Z25: KPK_ADP_2026-27_ICT_Opportunity.xlsx | AA25: ICT Projects
A26: KPK (Provincial ADP) | B26: 220154 | C26: Construction of District Judicial Complex Kohat | D26: Law & Justice | E26: Peshawar High Court | H26: Ongoing | I26: 1920.3 | J26: 560 | K26: 0.05 | L26: Low | M26: 28 | N26: 96.015 | O26: Facility: bofficesbbcomplexesbheadquartersecretariatdirectorate, bcourtsbjudicialjustice complex | P26: Yes | Q26: Yes | Z26: KPK_ADP_2026-27_ICT_Opportunity.xlsx | AA26: ICT Projects
A27: KPK (Provincial ADP) | B27: 260547 | C27: Establishment of Safe Cities at Divisional Headquarters (Kohat, Mardan / Mardan Package & Swat) | D27: Home | E27: Police | H27: New | I27: 3000 | J27: 500 | K27: 0.05 | L27: Low | M27: 25 | N27: 150 | O27: Facility: bofficesbbcomplexesbheadquartersecretariatdirectorate | P27: Yes | Q27: Yes | V27: Yes | X27: Yes | Z27: KPK_ADP_2026-27_ICT_Opportunity.xlsx | AA27: ICT Projects
A28: KPK (Provincial ADP) | B28: 150522 | C28: Establishment of Nowshera Medical College (Phase-I) | D28: Health | E28: Medical Education & Trg. | H28: Ongoing | I28: 2979.43 | J28: 500 | K28: 0.05 | L28: Low | M28: 25 | N28: 148.9715 | O28: Facility: bcollegesb, establishmentuniversitycollegeschoolhospitalinstitutecenter | P28: Yes | Q28: Yes | V28: Yes | Z28: KPK_ADP_2026-27_ICT_Opportunity.xlsx | AA28: ICT Projects
A29: KPK (Provincial ADP) | B29: 240004 | C29: Upgradation of Cat-D Hospital Sarwakai (Maula Khan Sari) to Cat-C Hospital Upper South Waziristan | D29: Health | E29: General Hospitals | H29: Ongoing | I29: 1200 | J29: 490 | K29: 0.05 | L29: Low | M29: 24.5 | N29: 60 | O29: Facility: bhospitalsb | P29: Yes | Q29: Yes | V29: Yes | Z29: KPK_ADP_2026-27_ICT_Opportunity.xlsx | AA29: ICT Projects
A30: KPK (Provincial ADP) | B30: 261235 | C30: Reconstruction / Rehabilitation of Fully Damaged Schools in District Khyber under Chinese Assistance Programme (Saving under ADP No. 191268/190280) | D30: Elementary & Secondary Education | E30: Foreign Assistance | H30: New | I30: 592.078 | J30: 487.201 | K30: 0.05 | L30: Low | M30: 5e-05 | N30: 29.6039 | O30: Facility: bschoolsb | P30: Yes | Q30: Yes | V30: Yes | Z30: KPK_ADP_2026-27_ICT_Opportunity.xlsx | AA30: ICT Projects
A31: KPK (Provincial ADP) | B31: 220650 | C31: Digitization (e-Governance) of Khyber Pakhtunkhwa (KFW Assisted) | D31: Science Technology & Information Technology | E31: Information Technology Board (KPITB) | H31: New | I31: 5110 | J31: 440 | K31: 0.7 | L31: High | M31: 3.5 | N31: 3577 | O31: Core-ICT: e-gov, digitiszation, information technology | P31: Yes | Q31: Yes | R31: Yes | S31: Yes | T31: Yes | U31: Yes | Z31: KPK_ADP_2026-27_ICT_Opportunity.xlsx | AA31: ICT Projects
A32: KPK (Provincial ADP) | B32: 210676 | C32: Up-gradation of Research Institutes to the Centers of Excellence. | D32: Agriculture | E32: Agriculture Research Systems | H32: Ongoing | I32: 1729.969 | J32: 423.269 | K32: 0.05 | L32: Low | M32: 21.16345 | N32: 86.49845 | O32: Facility: binstitutesb, bassemblybparliamentresearch stationinstitutecentercentreblaborator | P32: Yes | Q32: Yes | Z32: KPK_ADP_2026-27_ICT_Opportunity.xlsx | AA32: ICT Projects
A33: KPK (Provincial ADP) | B33: 210286 | C33: Provision of Express Lines to Cat-D Hospitals in Merged Areas (AIP). | D33: Health | E33: General Hospitals | H33: Ongoing | I33: 685.76 | J33: 423.268 | K33: 0.05 | L33: Low | M33: 21.1634 | N33: 34.288 | O33: Facility: bhospitalsb | P33: Yes | Q33: Yes | V33: Yes | Z33: KPK_ADP_2026-27_ICT_Opportunity.xlsx | AA33: ICT Projects
A34: KPK (Provincial ADP) | B34: 210493 | C34: Establishment of 67 ( 30:70 B&G) Primary Schools in Khyber Pakhtunkhwa | D34: Elementary & Secondary Education | E34: Primary Education | H34: Ongoing | I34: 740.347 | J34: 417.457 | K34: 0.05 | L34: Low | M34: 20.87285 | N34: 37.01735 | O34: Facility: bschoolsb, establishmentuniversitycollegeschoolhospitalinstitutecenter | P34: Yes | Q34: Yes | V34: Yes | Z34: KPK_ADP_2026-27_ICT_Opportunity.xlsx | AA34: ICT Projects
A35: KPK (Provincial ADP) | B35: 160187 | C35: Construction of Judicial Complexes, Swat | D35: Law & Justice | E35: Peshawar High Court | H35: Ongoing | I35: 1803.38 | J35: 407.976 | K35: 0.05 | L35: Low | M35: 20.3988 | N35: 90.169 | O35: Facility: bofficesbbcomplexesbheadquartersecretariatdirectorate, bcourtsbjudicialjustice complex | P35: Yes | Q35: Yes | Z35: KPK_ADP_2026-27_ICT_Opportunity.xlsx | AA35: ICT Projects
A36: KPK (Provincial ADP) | B36: 160595 | C36: Upgradation of 50 High Schools to Higher Secondary level (B&G) on need basis in Khyber Pakhtunkhwa (less 18 units) | D36: Elementary & Secondary Education | E36: Secondary Education | H36: Ongoing | I36: 1207.761 | J36: 405.311 | K36: 0.05 | L36: Low | M36: 20.26555 | N36: 60.38805 | O36: Facility: bschoolsb | P36: Yes | Q36: Yes | V36: Yes | Z36: KPK_ADP_2026-27_ICT_Opportunity.xlsx | AA36: ICT Projects
A37: KPK (Provincial ADP) | B37: 191400 | C37: Construction of Examination Halls in Schools on Need Basis (AIP) | D37: Elementary & Secondary Education | E37: Secondary Education | H37: Ongoing | I37: 1079.939 | J37: 400 | K37: 0.05 | L37: Low | M37: 20 | N37: 53.99695 | O37: Facility: bschoolsb | P37: Yes | Q37: Yes | V37: Yes | Z37: KPK_ADP_2026-27_ICT_Opportunity.xlsx | AA37: ICT Projects
A38: KPK (Provincial ADP) | B38: 250508 | C38: Construction of boys Hostels at Kohat Institute of Medical Sciences (KIMS), Kohat | D38: Health | E38: Medical Education & Trg. | H38: Ongoing | I38: 687.69 | J38: 400 | K38: 0.05 | L38: Low | M38: 20 | N38: 34.3845 | O38: Facility: binstitutesb, bhostelsb | P38: Yes | Q38: Yes | Z38: KPK_ADP_2026-27_ICT_Opportunity.xlsx | AA38: ICT Projects
A39: KPK (Provincial ADP) | B39: 200138 | C39: Provision of Additional infrastructure and repair of existing colleges | D39: Higher Education | E39: College Education | H39: Ongoing | I39: 1178.58 | J39: 392.98 | K39: 0.05 | L39: Low | M39: 19.649 | N39: 58.929 | O39: Facility: bcollegesb | P39: Yes | Q39: Yes | V39: Yes | Z39: KPK_ADP_2026-27_ICT_Opportunity.xlsx | AA39: ICT Projects
A40: KPK (Provincial ADP) | B40: 140813 | C40: Upgradation of Booni Hospital to Category-C Hospital, District Chitral. | D40: Health | E40: General Hospitals | H40: Ongoing | I40: 1083.955 | J40: 385.968 | K40: 0.05 | L40: Low | M40: 19.2984 | N40: 54.19775 | O40: Facility: bhospitalsb | P40: Yes | Q40: Yes | V40: Yes | Z40: KPK_ADP_2026-27_ICT_Opportunity.xlsx | AA40: ICT Projects
A41: KPK (Provincial ADP) | B41: 200096 | C41: Expansion/Upgradation of Khyber Girls Medical College, Peshawar for additional students of Merged Districts (AIP) | D41: Health | E41: Medical Education & Trg. | H41: Ongoing | I41: 452.607 | J41: 384.746 | K41: 0.05 | L41: Low | M41: 19.2373 | N41: 22.63035 | O41: Facility: bcollegesb | P41: Yes | Q41: Yes | V41: Yes | Z41: KPK_ADP_2026-27_ICT_Opportunity.xlsx | AA41: ICT Projects
A42: KPK (Provincial ADP) | B42: 260129 | C42: Establishment of Medical College in the existing building of Regional Professional Development Centre (Male) at Jamrud Khyber | D42: Health | E42: Medical Education & Trg. | H42: New | I42: 5000 | J42: 380 | K42: 0.05 | L42: Low | M42: 19 | N42: 250 | O42: Facility: bcollegesb, establishmentuniversitycollegeschoolhospitalinstitutecenter | P42: Yes | Q42: Yes | V42: Yes | Z42: KPK_ADP_2026-27_ICT_Opportunity.xlsx | AA42: ICT Projects
A43: KPK (Provincial ADP) | B43: 210273 | C43: Establishment of 260 Family Welfare Centers in Khyber Pakhtunkhwa. | D43: Population Welfare | E43: Population Welfare | H43: Ongoing | I43: 1976.093 | J43: 377 | K43: 0.05 | L43: Low | M43: 18.85 | N43: 98.80465 | O43: Facility: establishmentuniversitycollegeschoolhospitalinstitutecenter | P43: Yes | Q43: Yes | Z43: KPK_ADP_2026-27_ICT_Opportunity.xlsx | AA43: ICT Projects
A44: KPK (Provincial ADP) | B44: 210695 | C44: Construction of BS Blocks, Additional Class Rooms / missing / Security facilities in Govt. Colleges in Khyber Pakhtunkhwa | D44: Higher Education | E44: College Education | H44: Ongoing | I44: 1499.55 | J44: 375.02 | K44: 0.05 | L44: Low | M44: 18.751 | N44: 74.9775 | O44: Facility: bcollegesb | P44: Yes | Q44: Yes | V44: Yes | Z44: KPK_ADP_2026-27_ICT_Opportunity.xlsx | AA44: ICT Projects
A45: KPK (Provincial ADP) | B45: 250320 | C45: Establishment of 50 Primary schools with pre-fabricated structure in Khyber Pakhtunkhwa | D45: Elementary & Secondary Education | E45: Primary Education | H45: Ongoing | I45: 375 | J45: 375 | K45: 0.05 | L45: Low | M45: 18.75 | N45: 18.75 | O45: Facility: bschoolsb, establishmentuniversitycollegeschoolhospitalinstitutecenter | P45: Yes | Q45: Yes | V45: Yes | Z45: KPK_ADP_2026-27_ICT_Opportunity.xlsx | AA45: ICT Projects
A46: KPK (Provincial ADP) | B46: 170030 | C46: Pak Austria Facchochsule institute of Applied Sciences and technology (PAF-IAST) | D46: Higher Education | E46: University Education | H46: Ongoing | I46: 6782.529 | J46: 370 | K46: 0.05 | L46: Low | M46: 18.5 | N46: 339.12645 | O46: Facility: buniversit, binstitutesb | P46: Yes | Q46: Yes | V46: Yes | Z46: KPK_ADP_2026-27_ICT_Opportunity.xlsx | AA46: ICT Projects
A47: KPK (Provincial ADP) | B47: 190668 | C47: Settlement and Digitization of Land Record in Merged Districts (AIP) | D47: Board of Revenue | E47: Board of Revenue | H47: Ongoing | I47: 2703.95 | J47: 350 | K47: 0.7 | L47: High | M47: 245 | N47: 1892.765 | O47: Core-ICT: digitiszation, settlement and digiti; ICT-enabled: land record | P47: Yes | Q47: Yes | R47: Yes | S47: Yes | T47: Yes | Z47: KPK_ADP_2026-27_ICT_Opportunity.xlsx | AA47: ICT Projects
A48: KPK (Provincial ADP) | B48: 250933 | C48: F/S and Construction of Command & Control Center for Safe City Project Peshawar Adjacent to CPO office (KP) | D48: Home | E48: Police | H48: Ongoing | I48: 700 | J48: 350 | K48: 0.7 | L48: High | M48: 245 | N48: 490 | O48: Core-ICT: safe city, command and& control; Facility: bofficesbbcomplexesbheadquartersecretariatdirectorate | P48: Yes | Q48: Yes | R48: Yes | S48: Yes | T48: Yes | U48: Yes | V48: Yes | W48: Yes | X48: Yes | Z48: KPK_ADP_2026-27_ICT_Opportunity.xlsx | AA48: ICT Projects
A49: KPK (Provincial ADP) | B49: 260028 | C49: Construction of Residential accommodation on Need Basis for Judiciary | D49: Law & Justice | E49: Peshawar High Court | H49: New | I49: 1800 | J49: 350 | K49: 0.05 | L49: Low | M49: 17.5 | N49: 90 | O49: Facility: bcourtsbjudicialjustice complex | P49: Yes | Q49: Yes | Z49: KPK_ADP_2026-27_ICT_Opportunity.xlsx | AA49: ICT Projects
A50: KPK (Provincial ADP) | B50: 140307 | C50: F/S & Master Planning and Detailed Designing of Judicial Complex, Abbottabad | D50: Law & Justice | E50: Peshawar High Court | H50: Ongoing | I50: 1212.322 | J50: 331.604 | K50: 0.05 | L50: Low | M50: 16.5802 | N50: 60.6161 | O50: Facility: bofficesbbcomplexesbheadquartersecretariatdirectorate, bcourtsbjudicialjustice complex | P50: Yes | Q50: Yes | Z50: KPK_ADP_2026-27_ICT_Opportunity.xlsx | AA50: ICT Projects
A51: KPK (Provincial ADP) | B51: 250663 | C51: Promotion of climate smart Agriculture Practices through Extension Services in Khyber Pakhtunkhwa | D51: Agriculture | E51: Agriculture Extension | H51: Ongoing | I51: 1725 | J51: 318 | K51: 0.3 | L51: Medium | M51: 95.4 | N51: 517.5 | O51: ICT-enabled: smart irrigationagrifarmwatervillagetunnelmeter | P51: Yes | Q51: Yes | T51: Yes | W51: Yes | X51: Yes | Z51: KPK_ADP_2026-27_ICT_Opportunity.xlsx | AA51: ICT Projects
A52: KPK (Provincial ADP) | B52: 251639 | C52: Rehabilitation Structural Repair, Alteration and Addition of Existing Building of FRP (Police Lines Peshawar) | D52: Home | E52: Police | H52: Ongoing | I52: 314.52 | J52: 314.52 | K52: 0.05 | L52: Low | M52: 15.726 | N52: 15.726 | O52: Facility: bjailsbbprisonsbpolice stationlineposttrainingreformsfacilitheadquarter | P52: Yes | Q52: Yes | V52: Yes | X52: Yes | Z52: KPK_ADP_2026-27_ICT_Opportunity.xlsx | AA52: ICT Projects
A53: KPK (Provincial ADP) | B53: 220161 | C53: Acquisition of Land for New District Judicial Complex, Malakand | D53: Law & Justice | E53: Peshawar High Court | H53: Ongoing | I53: 312.4 | J53: 312.4 | K53: 0.05 | L53: Low | M53: 15.62 | N53: 15.62 | O53: Facility: bofficesbbcomplexesbheadquartersecretariatdirectorate, bcourtsbjudicialjustice complex | P53: Yes | Q53: Yes | Z53: KPK_ADP_2026-27_ICT_Opportunity.xlsx | AA53: ICT Projects
A54: KPK (Provincial ADP) | B54: 130618 | C54: Establishment of Kohat Institute of Medical Sciences (KIMS) | D54: Health | E54: Medical Education & Trg. | H54: Ongoing | I54: 2961.58 | J54: 311.644 | K54: 0.3 | L54: Medium | M54: 93.4932 | N54: 888.474 | O54: ICT-enabled: establishmentinstitute oftechnologexcellence; Facility: binstitutesb, establishment ofdepartmentauthoritycellunitwingofficedirectorateinstitute, establishmentuniversitycollegeschoolhospitalinstitutecenter | P54: Yes | Q54: Yes | T54: Yes | Z54: KPK_ADP_2026-27_ICT_Opportunity.xlsx | AA54: ICT Projects
A55: KPK (Provincial ADP) | B55: 160525 | C55: Establishment of Girls Cadet College at Mardan. | D55: Elementary & Secondary Education | E55: Secondary Education | H55: Ongoing | I55: 4260.129 | J55: 300.735 | K55: 0.05 | L55: Low | M55: 15.03675 | N55: 213.00645 | O55: Facility: bcollegesb, establishmentuniversitycollegeschoolhospitalinstitutecenter | P55: Yes | Q55: Yes | V55: Yes | Z55: KPK_ADP_2026-27_ICT_Opportunity.xlsx | AA55: ICT Projects
A56: KPK (Provincial ADP) | B56: 251528 | C56: Establishment of Peshawar Institute of Cardiology (PIC) Satellite Center at Bannu (PC-II Approved on 29-04-2026) | D56: Health | E56: General Hospitals | H56: Ongoing | I56: 8000 | J56: 300 | K56: 0.3 | L56: Medium | M56: 90 | N56: 2400 | O56: ICT-enabled: establishmentinstitute oftechnologexcellence; Facility: bhospitalsb, binstitutesb, establishment ofdepartmentauthoritycellunitwingofficedirectorateinstitute | P56: Yes | Q56: Yes | T56: Yes | V56: Yes | Z56: KPK_ADP_2026-27_ICT_Opportunity.xlsx | AA56: ICT Projects
A57: KPK (Provincial ADP) | B57: 195238 | C57: F/S & Construction of Police Stations and Police Posts including Levies Transformation (AIP) | D57: Multi Sectoral Development | E57: Special Forum | H57: Ongoing | I57: 7191.99 | J57: 300 | K57: 0.05 | L57: Low | M57: 15 | N57: 359.5995 | O57: Facility: bjailsbbprisonsbpolice stationlineposttrainingreformsfacilitheadquarter | P57: Yes | Q57: Yes | V57: Yes | X57: Yes | Z57: KPK_ADP_2026-27_ICT_Opportunity.xlsx | AA57: ICT Projects
A58: KPK (Provincial ADP) | B58: 200265 | C58: Construction of 07 District Judicial Complexes (AIP) | D58: Law & Justice | E58: Peshawar High Court | H58: Ongoing | I58: 4712.553 | J58: 300 | K58: 0.05 | L58: Low | M58: 15 | N58: 235.62765 | O58: Facility: bofficesbbcomplexesbheadquartersecretariatdirectorate, bcourtsbjudicialjustice complex | P58: Yes | Q58: Yes | Z58: KPK_ADP_2026-27_ICT_Opportunity.xlsx | AA58: ICT Projects
A59: KPK (Provincial ADP) | B59: 180599 | C59: Establishment of Paeds Hospital at District Swat (Phase-I). | D59: Health | E59: General Hospitals | H59: Ongoing | I59: 4271.816 | J59: 300 | K59: 0.05 | L59: Low | M59: 15 | N59: 213.5908 | O59: Facility: bhospitalsb, establishmentuniversitycollegeschoolhospitalinstitutecenter | P59: Yes | Q59: Yes | V59: Yes | Z59: KPK_ADP_2026-27_ICT_Opportunity.xlsx | AA59: ICT Projects
A60: KPK (Provincial ADP) | B60: 190524 | C60: Establishement of Women & Children Hospital in District Swabi (Phase-I) | D60: Health | E60: General Hospitals | H60: Ongoing | I60: 3845.644 | J60: 300 | K60: 0.05 | L60: Low | M60: 15 | N60: 192.2822 | O60: Facility: bhospitalsb | P60: Yes | Q60: Yes | V60: Yes | Z60: KPK_ADP_2026-27_ICT_Opportunity.xlsx | AA60: ICT Projects
A61: KPK (Provincial ADP) | B61: 261266 | C61: Establishment of Chief Minister Model Schools in Merged Area (Phase-I) | D61: Elementary & Secondary Education | E61: Primary Education | H61: New | I61: 3500 | J61: 300 | K61: 0.05 | L61: Low | M61: 15 | N61: 175 | O61: Facility: bschoolsb, establishmentuniversitycollegeschoolhospitalinstitutecenter | P61: Yes | Q61: Yes | V61: Yes | Z61: KPK_ADP_2026-27_ICT_Opportunity.xlsx | AA61: ICT Projects
A62: KPK (Provincial ADP) | B62: 261257 | C62: Construction / Rehabilitation of Tehsil Offices in KP. | D62: Urban Development | E62: Urban Development | H62: New | I62: 2000 | J62: 300 | K62: 0.05 | L62: Low | M62: 15 | N62: 100 | O62: Facility: bofficesbbcomplexesbheadquartersecretariatdirectorate, btehsilbcomplexoffice | P62: Yes | Q62: Yes | Z62: KPK_ADP_2026-27_ICT_Opportunity.xlsx | AA62: ICT Projects
A63: KPK (Provincial ADP) | B63: 240063 | C63: Transformation of Government Colleges into an institute of applied science and Technologies | D63: Higher Education | E63: College Education | H63: Ongoing | I63: 1923.263 | J63: 300 | K63: 0.05 | L63: Low | M63: 15 | N63: 96.16315 | O63: Facility: bcollegesb, binstitutesb | P63: Yes | Q63: Yes | V63: Yes | Z63: KPK_ADP_2026-27_ICT_Opportunity.xlsx | AA63: ICT Projects
A64: KPK (Provincial ADP) | B64: 200073 | C64: Reconstruction of Damaged School in Merged Districts (AIP) | D64: Elementary & Secondary Education | E64: Primary Education | H64: Ongoing | I64: 1485.5 | J64: 300 | K64: 0.05 | L64: Low | M64: 15 | N64: 74.275 | O64: Facility: bschoolsb | P64: Yes | Q64: Yes | V64: Yes | Z64: KPK_ADP_2026-27_ICT_Opportunity.xlsx | AA64: ICT Projects
A65: KPK (Provincial ADP) | B65: 260099 | C65: Feasibility Study and Establishment of General Hospital at Benazir Ground, Peshawar (Phase-I) | D65: Health | E65: General Hospitals | H65: New | I65: 4000 | J65: 270 | K65: 0.05 | L65: Low | M65: 13.5 | N65: 200 | O65: Facility: bhospitalsb, establishmentuniversitycollegeschoolhospitalinstitutecenter | P65: Yes | Q65: Yes | V65: Yes | Z65: KPK_ADP_2026-27_ICT_Opportunity.xlsx | AA65: ICT Projects
A66: KPK (Provincial ADP) | B66: 251311 | C66: Establishment of Project Management Unit for NHP & Cess Producing District in Khyber Pakhtunkhwa (Cost Rs. 500.000 Million) | D66: Royalties & Cess Development | E66: Regional Development | H66: Ongoing | I66: 570.915 | J66: 260 | K66: 0.05 | L66: Low | M66: 13 | N66: 28.54575 | O66: Facility: establishment ofdepartmentauthoritycellunitwingofficedirectorateinstitute | P66: Yes | Q66: Yes | Z66: KPK_ADP_2026-27_ICT_Opportunity.xlsx | AA66: ICT Projects
A67: KPK (Provincial ADP) | B67: 260433 | C67: Resilience, Early action and Disaster Readiness for Khyber Pakhtunkhwa (READY-KP) - Component of RR&S Department. | D67: Relief & Rehabilitation | E67: Relief and Rehabilitation | H67: New | I67: 15400 | J67: 258 | K67: 0.05 | L67: Low | M67: 10 | N67: 770 | O67: Institutional/reform programme - realistic minor MIS/digital & connectivity component | P67: Yes | Q67: Yes | Z67: KPK_ADP_2026-27_ICT_Opportunity.xlsx | AA67: ICT Projects
A68: KPK (Provincial ADP) | B68: 230115 | C68: Acquisition of 30 Kanal land for Construction of Tehsil Judicial Complex Puran, District Shangla | D68: Law & Justice | E68: Peshawar High Court | H68: Ongoing | I68: 600.783 | J68: 256.708 | K68: 0.05 | L68: Low | M68: 12.8354 | N68: 30.03915 | O68: Facility: bofficesbbcomplexesbheadquartersecretariatdirectorate, bcourtsbjudicialjustice complex, btehsilbcomplexoffice | P68: Yes | Q68: Yes | Z68: KPK_ADP_2026-27_ICT_Opportunity.xlsx | AA68: ICT Projects
A69: KPK (Provincial ADP) | B69: 200070 | C69: Up gradation of 70 Primary Schools to Middle level( AIP) | D69: Elementary & Secondary Education | E69: Secondary Education | H69: Ongoing | I69: 1042.3 | J69: 254.479 | K69: 0.05 | L69: Low | M69: 12.72395 | N69: 52.115 | O69: Facility: bschoolsb | P69: Yes | Q69: Yes | V69: Yes | Z69: KPK_ADP_2026-27_ICT_Opportunity.xlsx | AA69: ICT Projects
A70: KPK (Provincial ADP) | B70: 130446 | C70: F/S for Assessment of Residential Requirements, Master Planning & Designing of Judicial Complexes in Selected Districts of Khyber Pakhtunkhwa | D70: Law & Justice | E70: Peshawar High Court | H70: Ongoing | I70: 1458.08 | J70: 251.546 | K70: 0.05 | L70: Low | M70: 12.5773 | N70: 72.904 | O70: Facility: bofficesbbcomplexesbheadquartersecretariatdirectorate, bcourtsbjudicialjustice complex | P70: Yes | Q70: Yes | Z70: KPK_ADP_2026-27_ICT_Opportunity.xlsx | AA70: ICT Projects
A71: KPK (Provincial ADP) | B71: 190456 | C71: Establishment of Agriculture University at Swat. | D71: Agriculture | E71: Agriculture University | H71: Ongoing | I71: 7595.065 | J71: 250 | K71: 0.05 | L71: Low | M71: 12.5 | N71: 379.75325 | O71: Facility: buniversit, establishmentuniversitycollegeschoolhospitalinstitutecenter | P71: Yes | Q71: Yes | V71: Yes | Z71: KPK_ADP_2026-27_ICT_Opportunity.xlsx | AA71: ICT Projects
A72: KPK (Provincial ADP) | B72: 260492 | C72: Reconstruction of Malak Saad Shaheed Police Lines, Residential Hostel for Khyber Pakhtunkhwa Police | D72: Home | E72: Police | H72: New | I72: 2000 | J72: 250 | K72: 0.05 | L72: Low | M72: 12.5 | N72: 100 | O72: Facility: bhostelsb, bjailsbbprisonsbpolice stationlineposttrainingreformsfacilitheadquarter | P72: Yes | Q72: Yes | V72: Yes | X72: Yes | Z72: KPK_ADP_2026-27_ICT_Opportunity.xlsx | AA72: ICT Projects
A73: KPK (Provincial ADP) | B73: 150045 | C73: Establishment of Women University at Mardan | D73: Higher Education | E73: University Education | H73: Ongoing | I73: 1739.4 | J73: 250 | K73: 0.05 | L73: Low | M73: 12.5 | N73: 86.97 | O73: Facility: buniversit, establishmentuniversitycollegeschoolhospitalinstitutecenter | P73: Yes | Q73: Yes | V73: Yes | Z73: KPK_ADP_2026-27_ICT_Opportunity.xlsx | AA73: ICT Projects
A74: KPK (Provincial ADP) | B74: 170641 | C74: PC-I for upgradation of faculty of Agriculture Gomal University to University of Agriculture D.I Khan | D74: Agriculture | E74: Agriculture University | H74: Ongoing | I74: 3109.679 | J74: 239 | K74: 0.05 | L74: Low | M74: 11.95 | N74: 155.48395 | O74: Facility: buniversit | P74: Yes | Q74: Yes | V74: Yes | Z74: KPK_ADP_2026-27_ICT_Opportunity.xlsx | AA74: ICT Projects
A75: KPK (Provincial ADP) | B75: 240072 | C75: Strengthening of Existing Agriculture Research Station/ Institute at D.I Khan, Karak and Modal Farm Sangobhatti, Swabi | D75: Agriculture | E75: Agriculture Research Systems | H75: Ongoing | I75: 286.547 | J75: 236.547 | K75: 0.05 | L75: Low | M75: 11.82735 | N75: 14.32735 | O75: Facility: binstitutesb, bassemblybparliamentresearch stationinstitutecentercentreblaborator | P75: Yes | Q75: Yes | Z75: KPK_ADP_2026-27_ICT_Opportunity.xlsx | AA75: ICT Projects
A76: KPK (Provincial ADP) | B76: 191290 | C76: 180430 - Establishment of Model Schools in District South Waziristan. [MA] | D76: Elementary & Secondary Education | E76: Secondary Education | H76: Ongoing | I76: 337.129 | J76: 232.329 | K76: 0.05 | L76: Low | M76: 11.61645 | N76: 16.85645 | O76: Facility: bschoolsb, establishmentuniversitycollegeschoolhospitalinstitutecenter | P76: Yes | Q76: Yes | V76: Yes | Z76: KPK_ADP_2026-27_ICT_Opportunity.xlsx | AA76: ICT Projects
A77: KPK (Provincial ADP) | B77: 195164 | C77: Provision of Nurses & Paramedics for Health Facilities in Merged Districts. (AIP) | D77: Health | E77: Basic Health | H77: Ongoing | I77: 2429.374 | J77: 230 | K77: 0.05 | L77: Low | M77: 11.5 | N77: 121.4687 | O77: Facility: health facilityfacilitiescentrecenterunitcomplexcare | P77: Yes | Q77: Yes | Z77: KPK_ADP_2026-27_ICT_Opportunity.xlsx | AA77: ICT Projects
A78: KPK (Provincial ADP) | B78: 210684 | C78: Establishment of Digital City Haripur | D78: Science Technology & Information Technology | E78: Information Technology Board (KPITB) | H78: Ongoing | I78: 1642.344 | J78: 221.306 | K78: 0.7 | L78: High | M78: 154.9142 | N78: 1149.6408 | O78: Core-ICT: information technology, digital healtheducationagrigoverneconomservicpakistankpinfrastructuretransformationconnectcityskillinternshipcomplex; ICT-enabled: bdigitalb, establishmentinstitute oftechnologexcellence, digital | P78: Yes | Q78: Yes | R78: Yes | S78: Yes | T78: Yes | U78: Yes | Z78: KPK_ADP_2026-27_ICT_Opportunity.xlsx | AA78: ICT Projects
A79: KPK (Provincial ADP) | B79: 250375 | C79: Provision of Dialysis Services in DHQ Hospitals, Merged Districts | D79: Health | E79: Preventive Programme | H79: Ongoing | I79: 230.304 | J79: 215 | K79: 0.05 | L79: Low | M79: 10.75 | N79: 11.5152 | O79: Facility: bhospitalsb, bthqbbdhqbbrhcbbbhubbmchbcivil hospitals | P79: Yes | Q79: Yes | V79: Yes | Z79: KPK_ADP_2026-27_ICT_Opportunity.xlsx | AA79: ICT Projects
A80: KPK (Provincial ADP) | B80: 240239 | C80: Provision of additional funds for completion of ADP scheme "Up-gradation of SINOR, Swat, Code 200196" | D80: Health | E80: General Hospitals | H80: Ongoing | I80: 319.845 | J80: 207.845 | K80: 0.05 | L80: Low | M80: 10.39225 | N80: 15.99225 | O80: Facility: bhospitalsb | P80: Yes | Q80: Yes | V80: Yes | Z80: KPK_ADP_2026-27_ICT_Opportunity.xlsx | AA80: ICT Projects
A81: KPK (Provincial ADP) | B81: 240033 | C81: Construction of Tehsil Judicial Complex Balakot | D81: Law & Justice | E81: Peshawar High Court | H81: Ongoing | I81: 533.2 | J81: 205.5 | K81: 0.05 | L81: Low | M81: 10.275 | N81: 26.66 | O81: Facility: bofficesbbcomplexesbheadquartersecretariatdirectorate, bcourtsbjudicialjustice complex, btehsilbcomplexoffice | P81: Yes | Q81: Yes | Z81: KPK_ADP_2026-27_ICT_Opportunity.xlsx | AA81: ICT Projects
A82: KPK (Provincial ADP) | B82: 240029 | C82: Construction of Tehsil Judicial Complex at Serai Naurang | D82: Law & Justice | E82: Peshawar High Court | H82: Ongoing | I82: 384.4 | J82: 204.4 | K82: 0.05 | L82: Low | M82: 10.22 | N82: 19.22 | O82: Facility: bofficesbbcomplexesbheadquartersecretariatdirectorate, bcourtsbjudicialjustice complex, btehsilbcomplexoffice | P82: Yes | Q82: Yes | Z82: KPK_ADP_2026-27_ICT_Opportunity.xlsx | AA82: ICT Projects
A83: KPK (Provincial ADP) | B83: 250273 | C83: Construction of of 10 Govt. Colleges in Khyber Pakhtunkhwa on need basis(Including Degreee College for boys Mansehra City) | D83: Higher Education | E83: College Education | H83: Ongoing | I83: 7000 | J83: 200.04 | K83: 0.05 | L83: Low | M83: 10.002 | N83: 350 | O83: Facility: bcollegesb | P83: Yes | Q83: Yes | V83: Yes | Z83: KPK_ADP_2026-27_ICT_Opportunity.xlsx | AA83: ICT Projects
A84: KPK (Provincial ADP) | B84: 250177 | C84: F/S & Construction /Reconstruction of Police Lines, Command & Control Center for Safe City Project, two Police Stations and four Police Posts at District Bannu | D84: Home | E84: Police | H84: Ongoing | I84: 1090 | J84: 200 | K84: 0.7 | L84: High | M84: 140 | N84: 763 | O84: Core-ICT: safe city, command and& control; Facility: bjailsbbprisonsbpolice stationlineposttrainingreformsfacilitheadquarter | P84: Yes | Q84: Yes | R84: Yes | S84: Yes | T84: Yes | U84: Yes | V84: Yes | W84: Yes | X84: Yes | Z84: KPK_ADP_2026-27_ICT_Opportunity.xlsx | AA84: ICT Projects
A85: KPK (Provincial ADP) | B85: 261282 | C85: Increasing Access to Health Services Delivery through Telemedicine Under Served Areas of Khyber Pakhtunkhwa | D85: Health | E85: Basic Health | H85: New | I85: 1000 | J85: 200 | K85: 0.3 | L85: Medium | M85: 60 | N85: 300 | O85: ICT-enabled: tele-medicine, telemedicine | P85: Yes | Q85: Yes | T85: Yes | X85: Yes | Z85: KPK_ADP_2026-27_ICT_Opportunity.xlsx | AA85: ICT Projects
A86: KPK (Provincial ADP) | B86: 200266 | C86: Construction of 25 Tehsil Judicial Complexes (AIP) | D86: Law & Justice | E86: Peshawar High Court | H86: Ongoing | I86: 2745.9 | J86: 200 | K86: 0.05 | L86: Low | M86: 10 | N86: 137.295 | O86: Facility: bofficesbbcomplexesbheadquartersecretariatdirectorate, bcourtsbjudicialjustice complex, btehsilbcomplexoffice | P86: Yes | Q86: Yes | Z86: KPK_ADP_2026-27_ICT_Opportunity.xlsx | AA86: ICT Projects
A87: KPK (Provincial ADP) | B87: 160443 | C87: Construction of Purpose Built Building for Gajju Khan Medical College Swabi | D87: Health | E87: Medical Education & Trg. | H87: Ongoing | I87: 2592.447 | J87: 200 | K87: 0.05 | L87: Low | M87: 10 | N87: 129.62235 | O87: Facility: bcollegesb | P87: Yes | Q87: Yes | V87: Yes | Z87: KPK_ADP_2026-27_ICT_Opportunity.xlsx | AA87: ICT Projects
A88: KPK (Provincial ADP) | B88: 240062 | C88: Opening of 30 Degree Colleges in Rented Buildings in Khyber Pakhtunkhwa | D88: Higher Education | E88: College Education | H88: Ongoing | I88: 2039.81 | J88: 200 | K88: 0.05 | L88: Low | M88: 10 | N88: 101.9905 | O88: Facility: bcollegesb | P88: Yes | Q88: Yes | V88: Yes | Z88: KPK_ADP_2026-27_ICT_Opportunity.xlsx | AA88: ICT Projects
A89: KPK (Provincial ADP) | B89: 190428 | C89: Establishment of Model School Swabi | D89: Elementary & Secondary Education | E89: Secondary Education | H89: Ongoing | I89: 1681.043 | J89: 200 | K89: 0.05 | L89: Low | M89: 10 | N89: 84.05215 | O89: Facility: bschoolsb, establishmentuniversitycollegeschoolhospitalinstitutecenter | P89: Yes | Q89: Yes | V89: Yes | Z89: KPK_ADP_2026-27_ICT_Opportunity.xlsx | AA89: ICT Projects
A90: KPK (Provincial ADP) | B90: 250318 | C90: Construction of 500 Additional Classrooms in Primary schools with 02 rooms in merged districts | D90: Elementary & Secondary Education | E90: Primary Education | H90: Ongoing | I90: 1017.5 | J90: 200 | K90: 0.05 | L90: Low | M90: 10 | N90: 50.875 | O90: Facility: bschoolsb, bclassroom | P90: Yes | Q90: Yes | V90: Yes | Z90: KPK_ADP_2026-27_ICT_Opportunity.xlsx | AA90: ICT Projects
A91: KPK (Provincial ADP) | B91: 260115 | C91: F/S & Establishment of Health City (Phase-I) | D91: Health | E91: General Hospitals | H91: New | I91: 1000 | J91: 200 | K91: 0.05 | L91: Low | M91: 10 | N91: 50 | O91: Facility: bhospitalsb, establishmentuniversitycollegeschoolhospitalinstitutecenter | P91: Yes | Q91: Yes | V91: Yes | Z91: KPK_ADP_2026-27_ICT_Opportunity.xlsx | AA91: ICT Projects
A92: KPK (Provincial ADP) | B92: 260117 | C92: F/S & Establishment of Medical Complex (1000 beds) at Malakand | D92: Health | E92: General Hospitals | H92: New | I92: 500 | J92: 200 | K92: 0.05 | L92: Low | M92: 10 | N92: 25 | O92: Facility: bhospitalsb, bofficesbbcomplexesbheadquartersecretariatdirectorate, establishmentuniversitycollegeschoolhospitalinstitutecenter | P92: Yes | Q92: Yes | V92: Yes | Z92: KPK_ADP_2026-27_ICT_Opportunity.xlsx | AA92: ICT Projects
A93: KPK (Provincial ADP) | B93: 220235 | C93: Up-Gradation of Maidan Hospital from Cat-D to Cat- C Level Dir Lower. | D93: Health | E93: General Hospitals | H93: Ongoing | I93: 471.362 | J93: 200 | K93: 0.05 | L93: Low | M93: 10 | N93: 23.5681 | O93: Facility: bhospitalsb | P93: Yes | Q93: Yes | V93: Yes | Z93: KPK_ADP_2026-27_ICT_Opportunity.xlsx | AA93: ICT Projects
A94: KPK (Provincial ADP) | B94: 260032 | C94: Construction of Judicial Academy Peshawar | D94: Law & Justice | E94: Peshawar High Court | H94: New | I94: 7000 | J94: 198 | K94: 0.05 | L94: Low | M94: 9.9 | N94: 350 | O94: Facility: bacademyiesb, bcourtsbjudicialjustice complex | P94: Yes | Q94: Yes | Z94: KPK_ADP_2026-27_ICT_Opportunity.xlsx | AA94: ICT Projects
A95: KPK (Provincial ADP) | B95: 220287 | C95: Employable Digital Skills Initiatives for Youth of Khyber Pakhtunkhwa | D95: Science Technology & Information Technology | E95: Information Technology Board (KPITB) | H95: Ongoing | I95: 1256.594 | J95: 195 | K95: 0.7 | L95: High | M95: 136.5 | N95: 879.6158 | O95: Core-ICT: information technology, digital healtheducationagrigoverneconomservicpakistankpinfrastructuretransformationconnectcityskillinternshipcomplex; ICT-enabled: bdigitalb, skilldigitalbitbtech, digital | P95: Yes | Q95: Yes | R95: Yes | S95: Yes | T95: Yes | Z95: KPK_ADP_2026-27_ICT_Opportunity.xlsx | AA95: ICT Projects
A96: KPK (Provincial ADP) | B96: 260619 | C96: Upgradation of CHC Ayub Killi Tirah Shalobar, CD Milwat Akakhel to BHU and Estab. of BHU Hikmat Sipah in Khyber | D96: Health | E96: Basic Health | H96: New | I96: 750 | J96: 190.001 | K96: 0.05 | L96: Low | M96: 9.50005 | N96: 37.5 | O96: Facility: bthqbbdhqbbrhcbbbhubbmchbcivil hospitals | P96: Yes | Q96: Yes | Z96: KPK_ADP_2026-27_ICT_Opportunity.xlsx | AA96: ICT Projects
A97: KPK (Provincial ADP) | B97: 195162 | C97: Provision of Doctors at Health Facilties in Merged Districts (AIP) | D97: Health | E97: General Hospitals | H97: Ongoing | I97: 2017.422 | J97: 190 | K97: 0.05 | L97: Low | M97: 9.5 | N97: 100.8711 | O97: Facility: bhospitalsb | P97: Yes | Q97: Yes | V97: Yes | Z97: KPK_ADP_2026-27_ICT_Opportunity.xlsx | AA97: ICT Projects
A98: KPK (Provincial ADP) | B98: 200137 | C98: Purchase of Necessary Items (Furniture, Equipment, Plant & Machinery, Sport Goods, Computer & Allied Accessories, etc.) for Colleges on Need Basis. | D98: Higher Education | E98: College Education | H98: Ongoing | I98: 550 | J98: 188 | K98: 0.05 | L98: Low | M98: 9.4 | N98: 27.5 | O98: Facility: bcollegesb | P98: Yes | Q98: Yes | V98: Yes | Z98: KPK_ADP_2026-27_ICT_Opportunity.xlsx | AA98: ICT Projects
A99: KPK (Provincial ADP) | B99: 240032 | C99: Construction of Judicial Complex at Pattan | D99: Law & Justice | E99: Peshawar High Court | H99: Ongoing | I99: 526.7 | J99: 188 | K99: 0.05 | L99: Low | M99: 9.4 | N99: 26.335 | O99: Facility: bofficesbbcomplexesbheadquartersecretariatdirectorate, bcourtsbjudicialjustice complex | P99: Yes | Q99: Yes | Z99: KPK_ADP_2026-27_ICT_Opportunity.xlsx | AA99: ICT Projects
A100: KPK (Provincial ADP) | B100: 261154 | C100: Establishment of various types of basic health facilities on need basis in District Khyber | D100: Health | E100: Basic Health | H100: New | I100: 2000 | J100: 185 | K100: 0.05 | L100: Low | M100: 9.25 | N100: 100 | O100: Facility: health facilityfacilitiescentrecenterunitcomplexcare | P100: Yes | Q100: Yes | Z100: KPK_ADP_2026-27_ICT_Opportunity.xlsx | AA100: ICT Projects
...

Sheet Region Summary
A1: Region | B1: Project Count | C1: Total FY2026-27 Allocation (M PKR) | D1: Total ICT TAM on Allocation (M PKR)
A2: KPK (Provincial ADP) | B2: =COUNTIF('ICT Projects - Consolidated'!A2:A2555,A2) | C2: =SUMIF('ICT Projects - Consolidated'!A2:A2555,A2,'ICT Projects - Consolidated'!J2:J2555) | D2: =SUMIF('ICT Projects - Consolidated'!A2:A2555,A2,'ICT Projects - Consolidated'!M2:M2555)
A3: Sindh (Provincial ADP) | B3: =COUNTIF('ICT Projects - Consolidated'!A2:A2555,A3) | C3: =SUMIF('ICT Projects - Consolidated'!A2:A2555,A3,'ICT Projects - Consolidated'!J2:J2555) | D3: =SUMIF('ICT Projects - Consolidated'!A2:A2555,A3,'ICT Projects - Consolidated'!M2:M2555)
A4: Federal (PSDP) | B4: =COUNTIF('ICT Projects - Consolidated'!A2:A2555,A4) | C4: =SUMIF('ICT Projects - Consolidated'!A2:A2555,A4,'ICT Projects - Consolidated'!J2:J2555) | D4: =SUMIF('ICT Projects - Consolidated'!A2:A2555,A4,'ICT Projects - Consolidated'!M2:M2555)
A5: Balochistan (Provincial PSDP) | B5: =COUNTIF('ICT Projects - Consolidated'!A2:A2555,A5) | C5: =SUMIF('ICT Projects - Consolidated'!A2:A2555,A5,'ICT Projects - Consolidated'!J2:J2555) | D5: =SUMIF('ICT Projects - Consolidated'!A2:A2555,A5,'ICT Projects - Consolidated'!M2:M2555)
A6: Punjab (Provincial ADP) | B6: =COUNTIF('ICT Projects - Consolidated'!A2:A2555,A6) | C6: =SUMIF('ICT Projects - Consolidated'!A2:A2555,A6,'ICT Projects - Consolidated'!J2:J2555) | D6: =SUMIF('ICT Projects - Consolidated'!A2:A2555,A6,'ICT Projects - Consolidated'!M2:M2555)
A7: TOTAL | B7: =SUM(B2:B6) | C7: =SUM(C2:C6) | D7: =SUM(D2:D6)

Sheet Project News
A1: Project ID | B1: Project Name | C1: News Date | D1: News Title | E1: Keypoints | F1: Source | G1: URL | H1: Last Updated
A88: 210631 | B88: Khyber Pakhtunkhwa Rural Investment & Institutional Support Project (RIISP)(World Bank Assisted) | D88: Rural Investment and Institutional Support Project (RIISP) ... | E88: - GoKP requests $300 m IDA Credit from World Bank for rural investment and institutional support. - Funding aims to boost rural development and strengthen local institutions. | F88: kppra.gov.pk | G88: http://www.kppra.gov.pk/kppra/staff/force_download.php?file=dept%2Fupload%2F1705324703TORsandIrrigationandKPRIISPandFinal.pdf | H88: 46276.508
A89: 210631 | B89: Khyber Pakhtunkhwa Rural Investment & Institutional Support Project (RIISP)(World Bank Assisted) | D89: khyber pakhtunkhwa rural investment and institutional ... | E89: - World Bank funds $330 M Khyber Pakhtunkhwa Rural Investment Project to strengthen local institutions. - Project targets 4.5–5.5 million residents, building infrastructure in agriculture, water, roads, sanitation. | F89: documents1.worldbank.org | G89: https://documents1.worldbank.org/curated/en/099805312232218100/pdf/P1767800bb13ee050b40f0e1eee87aabc2.pdf | H89: 46276.508
A90: 210631 | B90: Khyber Pakhtunkhwa Rural Investment & Institutional Support Project (RIISP)(World Bank Assisted) | D90: Pakistan: World Bank Approves $200 million in support of Citizen-Driven Rural Investments and Post-Floods Rehabilitation for Khyber Pakhtunkhwa Province - Pakistan | ReliefWeb | E90: - World Bank approves $200 M for KPRIISP first phase, targeting 5.5 million rural households. - Project will rehabilitate flood damage, empower village councils, and strengthen service delivery. | F90: reliefweb.int | G90: https://reliefweb.int/report/pakistan/pakistan-world-bank-approves-200-million-support-citizen-driven-rural-investments-and-post-floods-rehabilitation-khyber-pakhtunkhwa-province | H90: 46276.508
A91: 210631 | B91: Khyber Pakhtunkhwa Rural Investment & Institutional Support Project (RIISP)(World Bank Assisted) | D91: + KP-Rural Investment and Institutional Support Project - “Governance Through Excellence” | E91: - Project on track: infrastructure rehabilitation, budget disbursement, safeguards, and community engagement progressing. - Modern tunnel farming delivers high‑quality vegetables, boosting farmer incomes and local markets. | F91: linkedin.com | G91: https://www.linkedin.com/company/kp-rural-investment-and-institutional-support-project | H91: 46276.508
A92: 210631 | B92: Khyber Pakhtunkhwa Rural Investment & Institutional Support Project (RIISP)(World Bank Assisted) | D92: Khyber Pakhtunkhwa Rural... - Contractor & Builders | E92: - Invitation for bids to rehabilitate solarized water schemes in Khyber district; deadline Oct 2026. - Project cost 70.053 M PKR, funded by World Bank IDA, using national competitive bidding. | F92: facebook.com | G92: https://www.facebook.com/100083372700792/posts/khyber-pakhtunkhwa-rural-investment-and-institutional-support-project/1095975029858244 | H92: 46276.508
A93: 210631 | B93: Khyber Pakhtunkhwa Rural Investment & Institutional Support Project (RIISP)(World Bank Assisted) | D93: government of khyber pakhtunkhwa | E93: - Project covers 14 districts, spans nine years with two four‑year phases under MPA. - Resettlement framework prepared to manage land acquisition, restrictions, and involuntary resettlement, supporting climate resilience. | F93: documents1.worldbank.org | G93: https://documents1.worldbank.org/curated/en/099041823174032123/pdf/P17678007e538b0e0804b0fd277ad94e7f.pdf | H93: 46276.508
A94: 210631 | B94: Khyber Pakhtunkhwa Rural Investment & Institutional Support Project (RIISP)(World Bank Assisted) | D94: Early Warning System | E94: - Expanding state services in merged Khyber Pakhtunkhwa areas via infrastructure and delivery system investments. - Strengthening local governance, flood protection, and project management through institutional support and capacity building. | F94: ewsdata.rightsindevelopment.org | G94: https://ewsdata.rightsindevelopment.org/projects/p176780-khyber-pakhtunkhwa-rural-investment-and-institutio | H94: 46276.508
A95: 210631 | B95: Khyber Pakhtunkhwa Rural Investment & Institutional Support Project (RIISP)(World Bank Assisted) | D95: World Bank's $200M Rural Investment Project in Khyber ... | E95: - World Bank funds $200M rural investment in Khyber Pakhtunkhwa. - Project gaining steady momentum. | F95: linkedin.com | G95: https://www.linkedin.com/posts/pakbanker_world-banks-200m-kp-rural-investment-project-activity-7441825411992276992-4h1Z | H95: 46276.508
A96: 210631 | B96: Khyber Pakhtunkhwa Rural Investment & Institutional Support Project (RIISP)(World Bank Assisted) | D96: A Meeting With The World Bank Mission Regarding KP-RIISP | E96: - Meeting with World Bank Mission held. - No project updates disclosed. | F96: pndkp.gov.pk | G96: https://pndkp.gov.pk/2025/12/05/a-meeting-with-the-world-bank-mission-regarding-kp-riisp | H96: 46276.508
A97: 210631 | B97: Khyber Pakhtunkhwa Rural Investment & Institutional Support Project (RIISP)(World Bank Assisted) | D97: Project Information Document - Khyber Pakhtunkhwa Rural Investment and Institutional Support Project - P176780 | E97: - No new project updates provided. - Project status remains unchanged. | F97: documents.worldbank.org | G97: https://documents.worldbank.org/en/publication/documents-reports/documentdetail/099042823082039352 | H97: 46276.508
